bbcpy/__init__.py
bbcpy/datatypes/__init__.py
bbcpy/datatypes/arrays.py
bbcpy/datatypes/eeg.py
bbcpy/functions/__init__.py
bbcpy/functions/base.py
bbcpy/functions/classifiers.py
bbcpy/functions/normalizations.py
bbcpy/functions/sourcespace.py
bbcpy/functions/spatial.py
bbcpy/functions/spectral.py
bbcpy/functions/statistics.py
bbcpy/functions/structural.py
bbcpy/functions/temporal.py
bbcpy/load/__init__.py
bbcpy/load/eeg.py
bbcpy/pipeline/__init__.py
bbcpy/pipeline/core.py
bbcpy/pipeline/model_selection.py
bbcpy/pipeline/pipeline.py
bbcpy/visual/__init__.py
bbcpy/visual/scalp.py
demos/__init__.py
demos/demo.py
demos/demo_wishart.py
demos/vitalbci/__init__.py
demos/vitalbci/viatlbci_Miklodyfire_analysis.py
demos/vitalbci/viatlbci_Miklodyfire_analysis_fb.py
demos/vitalbci/viatlbci_analysis.py
demos/vitalbci/vitalbci.py
demos/vitalbci/vitalbci2.py
demos/vitalbci/vitalbci_Miklodyfire.py
demos/vitalbci/vitalbci_Miklodyfire_fb_transfer.py
demos/vitalbci/vitalbci_funcs.py
demos/vitalbci/vitalbcigetmnt.py
tests/__init__.py
tests/bbcpy/__init__.py
tests/bbcpy/functions/__init__.py
tests/bbcpy/functions/test_normalizations.py
tests/bbcpy/functions/test_temporal.py
bbcpy-0.1.1.dist-info/LICENSE
bbcpy-0.1.1.dist-info/METADATA
bbcpy-0.1.1.dist-info/WHEEL
bbcpy-0.1.1.dist-info/top_level.txt
bbcpy-0.1.1.dist-info/RECORD
