Metadata-Version: 2.1
Name: bbcpy
Version: 0.1.1
Summary: A novel Python BCI toolbox
Home-page: https://github.com/bbcpy/bbcpy
Author: Neurotechnology Group TU Berlin
Author-email: bbcpy@tu-berlin.de
License: MIT
License-File: LICENSE
Requires-Dist: scikit-learn
Requires-Dist: pyriemann
Requires-Dist: numpy
Requires-Dist: scipy
Requires-Dist: matplotlib
Provides-Extra: tests
Requires-Dist: pytest ; extra == 'tests'
